cookiecutter_uv_package/__init__.py
cookiecutter_uv_package/cli.py
cookiecutter.json
hooks/post_gen_project.py
hooks/pre_gen_project.py
{{cookiecutter.project_slug}}/.gitignore
{{cookiecutter.project_slug}}/.release-please-manifest.json
{{cookiecutter.project_slug}}/Dockerfile
{{cookiecutter.project_slug}}/LICENSE
{{cookiecutter.project_slug}}/Makefile
{{cookiecutter.project_slug}}/README.md
{{cookiecutter.project_slug}}/SETUP.md
{{cookiecutter.project_slug}}/WORKFLOW.md
{{cookiecutter.project_slug}}/docker-compose.yml
{{cookiecutter.project_slug}}/pyproject.toml
{{cookiecutter.project_slug}}/release-please-config.json
{{cookiecutter.project_slug}}/.github/dependabot.yml
{{cookiecutter.project_slug}}/.github/workflows/checks.yml
{{cookiecutter.project_slug}}/.github/workflows/coverage.yml
{{cookiecutter.project_slug}}/.github/workflows/publish.yml
{{cookiecutter.project_slug}}/.github/workflows/release-please.yml
{{cookiecutter.project_slug}}/.github/workflows/setup-protection.yml
{{cookiecutter.project_slug}}/.github/workflows/uv-update.yml
{{cookiecutter.project_slug}}/examples/basic_usage.py
{{cookiecutter.project_slug}}/tests/__init__.py
{{cookiecutter.project_slug}}/tests/conftest.py
{{cookiecutter.project_slug}}/tests/test_{{cookiecutter.package_name}}.py
{{cookiecutter.project_slug}}/{{cookiecutter.package_name}}/__init__.py
{{cookiecutter.project_slug}}/{{cookiecutter.package_name}}/py.typed
cookiecutter_uv_package-1.0.9.dist-info/METADATA
cookiecutter_uv_package-1.0.9.dist-info/WHEEL
cookiecutter_uv_package-1.0.9.dist-info/entry_points.txt
cookiecutter_uv_package-1.0.9.dist-info/RECORD
