Metadata-Version: 2.4
Name: cookiecutter-uv-package
Version: 1.0.9
Summary: Modern cookiecutter template for creating Python packages with complete CI/CD setup and automatic PyPI publishing.
Project-URL: Homepage, https://github.com/serafinovsky/cookiecutter-uv-package
Project-URL: Documentation, https://serafinovsky.github.io/cookiecutter-uv-package
Project-URL: Repository, https://github.com/serafinovsky/cookiecutter-uv-package
Project-URL: Issues, https://github.com/serafinovsky/cookiecutter-uv-package/issues
Author-email: Mark Serafinovsky <m.serafinovsky@gmail.com>
License: MIT
Keywords: ci-cd,cookiecutter,development,github-actions,package,pypi,python,template
Classifier: Development Status :: 5 - Production/Stable
Classifier: Environment :: Web Environment
Classifier: Framework :: Hatch
Classifier: Framework :: Pytest
Classifier: Intended Audience :: Developers
Classifier: License :: OSI Approved :: MIT License
Classifier: Operating System :: OS Independent
Classifier: Programming Language :: Python :: 3
Classifier: Programming Language :: Python :: 3.9
Classifier: Programming Language :: Python :: 3.10
Classifier: Programming Language :: Python :: 3.11
Classifier: Programming Language :: Python :: 3.12
Classifier: Programming Language :: Python :: 3.13
Classifier: Topic :: Documentation
Classifier: Topic :: Internet :: WWW/HTTP :: Dynamic Content
Classifier: Topic :: Software Development :: Build Tools
Classifier: Topic :: Software Development :: Code Generators
Classifier: Topic :: Software Development :: Libraries :: Python Modules
Classifier: Topic :: Software Development :: Quality Assurance
Classifier: Topic :: Software Development :: Testing
Classifier: Typing :: Typed
Requires-Python: >=3.9
Requires-Dist: click==8.1.8
Requires-Dist: cookiecutter==2.6.0
